{
  "annee": 2024,
  "matiere": "physique_chimie",
  "source_pdf": "Sujet-complet-2024.pdf",
  "source_corrige": "corrige-PC-2024.pdf",
  "exercices": [
    {
      "id": "PC2024-I",
      "titre": "Diffraction et interférences",
      "chapitre": "ondes_optique",
      "points_total": 11,
      "contexte": {
        "texte": "Un faisceau laser de longueur d'onde λ éclaire deux fentes d'Young séparées d'une distance a = 0,15 mm. On observe une figure d'interférences sur un écran placé à une distance D = 1,20 m. L'interfrange mesurée sur l'écran est i = 4,0 mm.",
        "schemas": [
          {
            "source": "pdf_crop",
            "pdf": "Sujet-complet-2024.pdf",
            "page": 6,
            "crop": {"top": 0.05, "bottom": 0.5, "left": 0.0, "right": 1.0},
            "description": "Schéma fentes d'Young"
          }
        ]
      },
      "questions": [
        {
          "id": "PC2024-I-1",
          "enonce": "Identifier le phénomène optique",
          "type": "manuscrit",
          "champs_reponse": [
            {"label": "Phénomène :", "id": "phenomene", "width": "large"}
          ],
          "points": 3,
          "reponse_attendue": "Phénomène de diffraction et interférences lumineuses.",
          "cours_associe": "Ondes lumineuses.",
          "indice": "Pensez aux fentes d'Young."
        },
        {
          "id": "PC2024-I-2",
          "enonce": "Calcul de la longueur d'onde λ",
          "type": "manuscrit",
          "champs_reponse": [
            {"label": "$\\lambda$ =", "id": "lambda_calcul", "width": "large"}
          ],
          "points": 8,
          "reponse_attendue": "λ = (i * a) / D = (4,0.10^-3 * 0,15.10^-3) / 1,20 = 5,0.10^-7 m = 500 nm.",
          "cours_associe": "Interférences.",
          "indice": "Utilisez la formule de l'interfrange i = lambda * D / a."
        }
      ]
    },
    {
      "id": "PC2024-II",
      "titre": "Estérification",
      "chapitre": "chimie_organique",
      "points_total": 13,
      "contexte": {
        "texte": "On réalise une synthèse organique.",
        "schemas": [
          {
            "source": "pdf_crop",
            "pdf": "Sujet-complet-2024.pdf",
            "page": 7,
            "crop": {"top": 0.05, "bottom": 0.5, "left": 0.0, "right": 1.0},
            "description": "Montage à reflux"
          }
        ]
      },
      "questions": [
        {
          "id": "PC2024-II-1",
          "enonce": "Équation de la réaction",
          "type": "manuscrit",
          "champs_reponse": [
            {"label": "Équation :", "id": "equation", "width": "large"}
          ],
          "points": 5,
          "reponse_attendue": "Acide carboxylique + Alcool = Ester + Eau",
          "cours_associe": "Réactions d'estérification.",
          "indice": "N'oubliez pas que la réaction est équilibrée."
        },
        {
          "id": "PC2024-II-2",
          "enonce": "Calcul du rendement",
          "type": "manuscrit",
          "champs_reponse": [
            {"label": "$\\\\eta$ =", "id": "rendement", "width": "large"}
          ],
          "points": 8,
          "reponse_attendue": "Rendement = n_exp / n_theo.",
          "cours_associe": "Rendement d'une synthèse organique.",
          "indice": "Identifiez le réactif limitant."
        }
      ]
    },
    {
      "id": "PC2024-III",
      "titre": "Saut à ski",
      "chapitre": "mecanique",
      "points_total": 16,
      "contexte": {
        "texte": "Étude du mouvement d'un sauteur à ski.",
        "schemas": [
          {
            "source": "pdf_crop",
            "pdf": "Sujet-complet-2024.pdf",
            "page": 8,
            "crop": {"top": 0.05, "bottom": 0.5, "left": 0.0, "right": 1.0},
            "description": "Schéma saut à ski"
          }
        ]
      },
      "questions": [
        {
          "id": "PC2024-III-1",
          "enonce": "Bilan des forces",
          "type": "manuscrit",
          "champs_reponse": [
            {"label": "Forces :", "id": "forces", "width": "large"}
          ],
          "points": 6,
          "reponse_attendue": "Poids, réaction du support, frottements.",
          "cours_associe": "Mécanique du point.",
          "indice": "Faites un schéma."
        },
        {
          "id": "PC2024-III-2",
          "enonce": "Application du théorème de l'énergie cinétique",
          "type": "manuscrit",
          "champs_reponse": [
            {"label": "$\\Delta E_c$ =", "id": "delta_ec", "width": "large"}
          ],
          "points": 10,
          "reponse_attendue": "Delta Ec = Somme des travaux des forces.",
          "cours_associe": "Énergétique.",
          "indice": "Le travail du poids ne dépend que de l'altitude."
        }
      ]
    }
  ]
}